[
  {
    "name": "cube_m_0",
    "type": "cube_m",
    "position": {
      "x": 0.248,
      "y": 0.202,
      "z": 1.05
    },
    "rotation": {
      "roll": 0.0,
      "pitch": 0.0,
      "yaw": 1.41
    },
    "color": {
      "r": 0.52,
      "g": 0.25,
      "b": 0.48,
      "a": 1.0
    }
  },
  {
    "name": "cylinder_l_1",
    "type": "cylinder_l",
    "position": {
      "x": 0.458,
      "y": -0.159,
      "z": 1.05
    },
    "rotation": {
      "roll": 0.0,
      "pitch": 0.0,
      "yaw": 0.83
    },
    "color": {
      "r": 0.86,
      "g": 0.49,
      "b": 0.51,
      "a": 1.0
    }
  },
  {
    "name": "cylinder_s_2",
    "type": "cylinder_s",
    "position": {
      "x": 0.203,
      "y": 0.002,
      "z": 1.05
    },
    "rotation": {
      "roll": 0.0,
      "pitch": 0.0,
      "yaw": 3.75
    },
    "color": {
      "r": 0.85,
      "g": 0.52,
      "b": 0.69,
      "a": 1.0
    }
  },
  {
    "name": "cube_l_3",
    "type": "cube_l",
    "position": {
      "x": 0.377,
      "y": -0.214,
      "z": 1.05
    },
    "rotation": {
      "roll": 0.0,
      "pitch": 0.0,
      "yaw": 3.39
    },
    "color": {
      "r": 0.91,
      "g": 0.1,
      "b": 0.15,
      "a": 1.0
    }
  },
  {
    "name": "cube_m_4",
    "type": "cube_m",
    "position": {
      "x": 0.253,
      "y": -0.213,
      "z": 1.05
    },
    "rotation": {
      "roll": 0.0,
      "pitch": 0.0,
      "yaw": 1.44
    },
    "color": {
      "r": 0.52,
      "g": 0.82,
      "b": 0.37,
      "a": 1.0
    }
  }
]