[
  {
    "name": "cube_s_0",
    "type": "cube_s",
    "position": {
      "x": 0.298,
      "y": 0.077,
      "z": 1.05
    },
    "rotation": {
      "roll": 0.0,
      "pitch": 0.0,
      "yaw": 3.54
    },
    "color": {
      "r": 0.36,
      "g": 0.17,
      "b": 0.32,
      "a": 1.0
    }
  },
  {
    "name": "cylinder_s_1",
    "type": "cylinder_s",
    "position": {
      "x": 0.23,
      "y": 0.112,
      "z": 1.05
    },
    "rotation": {
      "roll": 0.0,
      "pitch": 0.0,
      "yaw": 6.0
    },
    "color": {
      "r": 0.96,
      "g": 0.23,
      "b": 0.9,
      "a": 1.0
    }
  },
  {
    "name": "cube_s_2",
    "type": "cube_s",
    "position": {
      "x": 0.427,
      "y": -0.185,
      "z": 1.05
    },
    "rotation": {
      "roll": 0.0,
      "pitch": 0.0,
      "yaw": 3.59
    },
    "color": {
      "r": 0.51,
      "g": 0.3,
      "b": 0.13,
      "a": 1.0
    }
  },
  {
    "name": "sphere_m_3",
    "type": "sphere_m",
    "position": {
      "x": 0.275,
      "y": -0.21,
      "z": 1.05
    },
    "rotation": {
      "roll": 0.0,
      "pitch": 0.0,
      "yaw": 1.2
    },
    "color": {
      "r": 0.41,
      "g": 0.56,
      "b": 0.37,
      "a": 1.0
    }
  },
  {
    "name": "cube_s_4",
    "type": "cube_s",
    "position": {
      "x": 0.451,
      "y": -0.016,
      "z": 1.05
    },
    "rotation": {
      "roll": 0.0,
      "pitch": 0.0,
      "yaw": 2.94
    },
    "color": {
      "r": 0.12,
      "g": 0.68,
      "b": 0.22,
      "a": 1.0
    }
  }
]