[
  {
    "name": "cylinder_m_0",
    "type": "cylinder_m",
    "position": {
      "x": 0.226,
      "y": -0.145,
      "z": 1.05
    },
    "rotation": {
      "roll": 0.0,
      "pitch": 0.0,
      "yaw": 4.15
    },
    "color": {
      "r": 0.81,
      "g": 0.93,
      "b": 0.84,
      "a": 1.0
    }
  },
  {
    "name": "cylinder_s_1",
    "type": "cylinder_s",
    "position": {
      "x": 0.334,
      "y": 0.219,
      "z": 1.05
    },
    "rotation": {
      "roll": 0.0,
      "pitch": 0.0,
      "yaw": 0.3
    },
    "color": {
      "r": 0.12,
      "g": 0.14,
      "b": 0.62,
      "a": 1.0
    }
  },
  {
    "name": "cube_m_2",
    "type": "cube_m",
    "position": {
      "x": 0.496,
      "y": 0.152,
      "z": 1.05
    },
    "rotation": {
      "roll": 0.0,
      "pitch": 0.0,
      "yaw": 0.21
    },
    "color": {
      "r": 0.26,
      "g": 0.13,
      "b": 0.95,
      "a": 1.0
    }
  },
  {
    "name": "cylinder_l_3",
    "type": "cylinder_l",
    "position": {
      "x": 0.354,
      "y": -0.047,
      "z": 1.05
    },
    "rotation": {
      "roll": 0.0,
      "pitch": 0.0,
      "yaw": 2.92
    },
    "color": {
      "r": 0.63,
      "g": 0.87,
      "b": 0.96,
      "a": 1.0
    }
  },
  {
    "name": "sphere_m_4",
    "type": "sphere_m",
    "position": {
      "x": 0.466,
      "y": 0.105,
      "z": 1.05
    },
    "rotation": {
      "roll": 0.0,
      "pitch": 0.0,
      "yaw": 2.44
    },
    "color": {
      "r": 0.32,
      "g": 0.17,
      "b": 0.84,
      "a": 1.0
    }
  }
]