[
  {
    "name": "cube_s_0",
    "type": "cube_s",
    "position": {
      "x": 0.454,
      "y": -0.005,
      "z": 1.05
    },
    "rotation": {
      "roll": 0.0,
      "pitch": 0.0,
      "yaw": 3.24
    },
    "color": {
      "r": 0.21,
      "g": 0.5,
      "b": 0.71,
      "a": 1.0
    }
  },
  {
    "name": "cube_m_1",
    "type": "cube_m",
    "position": {
      "x": 0.483,
      "y": 0.097,
      "z": 1.05
    },
    "rotation": {
      "roll": 0.0,
      "pitch": 0.0,
      "yaw": 2.62
    },
    "color": {
      "r": 0.96,
      "g": 0.68,
      "b": 0.8,
      "a": 1.0
    }
  },
  {
    "name": "cube_s_2",
    "type": "cube_s",
    "position": {
      "x": 0.101,
      "y": 0.011,
      "z": 1.05
    },
    "rotation": {
      "roll": 0.0,
      "pitch": 0.0,
      "yaw": 2.61
    },
    "color": {
      "r": 0.71,
      "g": 0.77,
      "b": 0.43,
      "a": 1.0
    }
  },
  {
    "name": "cube_s_3",
    "type": "cube_s",
    "position": {
      "x": 0.213,
      "y": 0.033,
      "z": 1.05
    },
    "rotation": {
      "roll": 0.0,
      "pitch": 0.0,
      "yaw": 4.05
    },
    "color": {
      "r": 0.81,
      "g": 0.23,
      "b": 0.45,
      "a": 1.0
    }
  },
  {
    "name": "cube_s_4",
    "type": "cube_s",
    "position": {
      "x": 0.295,
      "y": -0.268,
      "z": 1.05
    },
    "rotation": {
      "roll": 0.0,
      "pitch": 0.0,
      "yaw": 4.55
    },
    "color": {
      "r": 0.44,
      "g": 0.13,
      "b": 0.31,
      "a": 1.0
    }
  }
]